{
  "generated_at": "2026-06-04T01:05:22.061411+09:00",
  "tickers": [
    "252670.KS",
    "114800.KS",
    "0193W0",
    "0193T0",
    "252710.KS",
    "0195R0",
    "462330.KS",
    "233740.KS",
    "037560.KS",
    "0195S0",
    "000990.KS",
    "086520.KS",
    "042700.KS",
    "GOOGL",
    "AMZN",
    "NOC",
    "INTC",
    "207940.KS",
    "MCHP",
    "051910.KS",
    "COP",
    "NIO",
    "CVX",
    "068270.KS",
    "JPM",
    "373220.KS",
    "BA",
    "NFLX",
    "MSFT",
    "AMAT",
    "096770.KS",
    "010950.KS",
    "035420.KS",
    "005380.KS",
    "000270.KS",
    "META",
    "247540.KS",
    "RIVN",
    "BAC",
    "WFC",
    "PFE",
    "NVDA",
    "000660.KS",
    "005930.KS",
    "AVGO",
    "466920.KS",
    "035720.KS"
  ],
  "details": {
    "252670.KS": {
      "ticker": "252670.KS",
      "source": "kis_volume_surge",
      "signal_type": "volume_surge",
      "name": "KODEX 200선물인버스2X",
      "volume_rank": 1,
      "current_price": 76.0,
      "volume": 11458992289,
      "change_rate": 0.0,
      "market": "KR",
      "currency": "KRW",
      "portfolio": false,
      "asset_type": "stock"
    },
    "114800.KS": {
      "ticker": "114800.KS",
      "source": "kis_volume_surge",
      "signal_type": "volume_surge",
      "name": "KODEX 인버스",
      "volume_rank": 2,
      "current_price": 924.0,
      "volume": 1191968288,
      "change_rate": 0.11,
      "market": "KR",
      "currency": "KRW",
      "portfolio": false,
      "asset_type": "stock"
    },
    "0193W0": {
      "ticker": "0193W0",
      "source": "kis_volume_surge",
      "signal_type": "volume_surge",
      "name": "KODEX 삼성전자단일종목레버리지",
      "volume_rank": 3,
      "current_price": 31325.0,
      "volume": 112870987,
      "change_rate": 6.73,
      "market": "US",
      "currency": "$",
      "portfolio": false,
      "asset_type": "stock"
    },
    "0193T0": {
      "ticker": "0193T0",
      "source": "kis_volume_surge",
      "signal_type": "volume_surge",
      "name": "KODEX SK하이닉스단일종목레버리지",
      "volume_rank": 4,
      "current_price": 30545.0,
      "volume": 100087348,
      "change_rate": -1.78,
      "market": "US",
      "currency": "$",
      "portfolio": false,
      "asset_type": "stock"
    },
    "252710.KS": {
      "ticker": "252710.KS",
      "source": "kis_volume_surge",
      "signal_type": "volume_surge",
      "name": "TIGER 200선물인버스2X",
      "volume_rank": 5,
      "current_price": 80.0,
      "volume": 97752147,
      "change_rate": -3.61,
      "market": "KR",
      "currency": "KRW",
      "portfolio": false,
      "asset_type": "stock"
    },
    "0195R0": {
      "ticker": "0195R0",
      "source": "kis_volume_surge",
      "signal_type": "volume_surge",
      "name": "TIGER 삼성전자단일종목레버리지",
      "volume_rank": 6,
      "current_price": 28950.0,
      "volume": 92153646,
      "change_rate": 6.49,
      "market": "US",
      "currency": "$",
      "portfolio": false,
      "asset_type": "stock"
    },
    "462330.KS": {
      "ticker": "462330.KS",
      "source": "kis_volume_surge",
      "signal_type": "volume_surge",
      "name": "KODEX 2차전지산업레버리지",
      "volume_rank": 7,
      "current_price": 1991.0,
      "volume": 80459143,
      "change_rate": -8.88,
      "market": "KR",
      "currency": "KRW",
      "portfolio": false,
      "asset_type": "stock"
    },
    "233740.KS": {
      "ticker": "233740.KS",
      "source": "kis_volume_surge",
      "signal_type": "volume_surge",
      "name": "KODEX 코스닥150레버리지",
      "volume_rank": 8,
      "current_price": 13330.0,
      "volume": 78442609,
      "change_rate": -5.19,
      "market": "KR",
      "currency": "KRW",
      "portfolio": false,
      "asset_type": "stock"
    },
    "037560.KS": {
      "ticker": "037560.KS",
      "source": "kis_volume_surge",
      "signal_type": "volume_surge",
      "name": "LG헬로비전",
      "volume_rank": 9,
      "current_price": 3170.0,
      "volume": 65929784,
      "change_rate": 10.84,
      "market": "KR",
      "currency": "KRW",
      "portfolio": false,
      "asset_type": "stock"
    },
    "0195S0": {
      "ticker": "0195S0",
      "source": "kis_volume_surge",
      "signal_type": "volume_surge",
      "name": "TIGER SK하이닉스단일종목레버리지",
      "volume_rank": 10,
      "current_price": 26015.0,
      "volume": 64729250,
      "change_rate": -1.96,
      "market": "US",
      "currency": "$",
      "portfolio": false,
      "asset_type": "stock"
    },
    "000990.KS": {
      "ticker": "000990.KS",
      "name": "000990.KS",
      "market": "KR",
      "currency": "₩",
      "portfolio": false,
      "asset_type": "stock",
      "source": "candidate:hunt",
      "status": "open",
      "detected_at": "2026-06-04T01:04:43.401153+09:00",
      "candidate_id": "cand_bbe2b16277b142a6a7828dd446b0b90a",
      "source_system": "jackal",
      "source_event_type": "hunt",
      "signal_family": "oversold_rebound",
      "quality_label": null,
      "quality_score": 24.0,
      "reason": "oversold_rebound"
    },
    "086520.KS": {
      "ticker": "086520.KS",
      "name": "086520.KS",
      "market": "KR",
      "currency": "₩",
      "portfolio": false,
      "asset_type": "stock",
      "source": "candidate:hunt",
      "status": "open",
      "detected_at": "2026-06-04T01:04:42.945989+09:00",
      "candidate_id": "cand_e9910f7b5dcc4e139b688417656086e2",
      "source_system": "jackal",
      "source_event_type": "hunt",
      "signal_family": "rotation",
      "quality_label": null,
      "quality_score": 24.0,
      "reason": "rotation"
    },
    "042700.KS": {
      "ticker": "042700.KS",
      "name": "042700.KS",
      "market": "KR",
      "currency": "₩",
      "portfolio": false,
      "asset_type": "stock",
      "source": "candidate:hunt",
      "status": "open",
      "detected_at": "2026-06-04T01:04:42.496138+09:00",
      "candidate_id": "cand_60c0f71e10994f11a9fbcb392a9762d5",
      "source_system": "jackal",
      "source_event_type": "hunt",
      "signal_family": "rotation",
      "quality_label": null,
      "quality_score": 24.0,
      "reason": "ma_reclaim"
    },
    "GOOGL": {
      "ticker": "GOOGL",
      "name": "GOOGL",
      "market": "US",
      "currency": "$",
      "portfolio": false,
      "asset_type": "stock",
      "source": "candidate:hunt",
      "status": "open",
      "detected_at": "2026-06-04T01:04:42.050251+09:00",
      "candidate_id": "cand_f0e8ab7fd72741b0b5f039220e6227e5",
      "source_system": "jackal",
      "source_event_type": "hunt",
      "signal_family": "momentum_pullback",
      "quality_label": null,
      "quality_score": 24.0,
      "reason": "oversold_rebound"
    },
    "AMZN": {
      "ticker": "AMZN",
      "name": "AMZN",
      "market": "US",
      "currency": "$",
      "portfolio": false,
      "asset_type": "stock",
      "source": "candidate:hunt",
      "status": "open",
      "detected_at": "2026-06-04T01:04:41.594521+09:00",
      "candidate_id": "cand_129d1bf958484591a1d4eeb4e635c057",
      "source_system": "jackal",
      "source_event_type": "hunt",
      "signal_family": "momentum_pullback",
      "quality_label": null,
      "quality_score": 29.0,
      "reason": "momentum_pullback"
    },
    "NOC": {
      "ticker": "NOC",
      "name": "NOC",
      "market": "US",
      "currency": "$",
      "portfolio": false,
      "asset_type": "stock",
      "source": "candidate:hunt",
      "status": "open",
      "detected_at": "2026-06-03T09:17:55.072664+09:00",
      "candidate_id": "cand_63bb316a559c49a88e8d736e770f3a48",
      "source_system": "jackal",
      "source_event_type": "hunt",
      "signal_family": "oversold_rebound",
      "quality_label": null,
      "quality_score": 24.0,
      "reason": "oversold_rebound"
    },
    "INTC": {
      "ticker": "INTC",
      "name": "INTC",
      "market": "US",
      "currency": "$",
      "portfolio": false,
      "asset_type": "stock",
      "source": "candidate:hunt",
      "status": "open",
      "detected_at": "2026-06-03T09:17:54.610840+09:00",
      "candidate_id": "cand_d5d35fbe166c4ba3a3888c731f40afc2",
      "source_system": "jackal",
      "source_event_type": "hunt",
      "signal_family": "rotation",
      "quality_label": null,
      "quality_score": 24.0,
      "reason": "rotation"
    },
    "207940.KS": {
      "ticker": "207940.KS",
      "name": "207940.KS",
      "market": "KR",
      "currency": "₩",
      "portfolio": false,
      "asset_type": "stock",
      "source": "candidate:hunt",
      "status": "open",
      "detected_at": "2026-06-03T00:44:12.140072+09:00",
      "candidate_id": "cand_f68d5accac704910b9103793ceaa15cf",
      "source_system": "jackal",
      "source_event_type": "hunt",
      "signal_family": "rotation",
      "quality_label": null,
      "quality_score": 24.0,
      "reason": "rotation"
    },
    "MCHP": {
      "ticker": "MCHP",
      "name": "MCHP",
      "market": "US",
      "currency": "$",
      "portfolio": false,
      "asset_type": "stock",
      "source": "candidate:hunt",
      "status": "open",
      "detected_at": "2026-06-02T08:56:55.265122+09:00",
      "candidate_id": "cand_e4fad341b1a24003a18ddb4304498a06",
      "source_system": "jackal",
      "source_event_type": "hunt",
      "signal_family": "rotation",
      "quality_label": null,
      "quality_score": 24.0,
      "reason": "oversold_rebound"
    },
    "051910.KS": {
      "ticker": "051910.KS",
      "name": "051910.KS",
      "market": "KR",
      "currency": "₩",
      "portfolio": false,
      "asset_type": "stock",
      "source": "candidate:hunt",
      "status": "open",
      "detected_at": "2026-06-02T02:06:30.560571+09:00",
      "candidate_id": "cand_c86776ab995342b79e182bf953572d0c",
      "source_system": "jackal",
      "source_event_type": "hunt",
      "signal_family": "ma_reclaim",
      "quality_label": null,
      "quality_score": 24.0,
      "reason": "oversold_rebound"
    },
    "COP": {
      "ticker": "COP",
      "name": "COP",
      "market": "US",
      "currency": "$",
      "portfolio": false,
      "asset_type": "stock",
      "source": "candidate:hunt",
      "status": "open",
      "detected_at": "2026-06-01T08:44:57.938062+09:00",
      "candidate_id": "cand_3daae0341db44b08b23a7f1466832960",
      "source_system": "jackal",
      "source_event_type": "hunt",
      "signal_family": "divergence",
      "quality_label": null,
      "quality_score": 24.0,
      "reason": "divergence"
    },
    "NIO": {
      "ticker": "NIO",
      "name": "NIO",
      "market": "US",
      "currency": "$",
      "portfolio": false,
      "asset_type": "stock",
      "source": "candidate:hunt",
      "status": "open",
      "detected_at": "2026-05-29T08:56:23.917806+09:00",
      "candidate_id": "cand_a9d090b0ddd04e2ca5070cf5b3befa8a",
      "source_system": "jackal",
      "source_event_type": "hunt",
      "signal_family": "divergence",
      "quality_label": null,
      "quality_score": 24.0,
      "reason": "divergence"
    },
    "CVX": {
      "ticker": "CVX",
      "name": "CVX",
      "market": "US",
      "currency": "$",
      "portfolio": false,
      "asset_type": "stock",
      "source": "candidate:hunt",
      "status": "open",
      "detected_at": "2026-05-28T23:53:27.958515+09:00",
      "candidate_id": "cand_3d4d2ff5a2b14340b24a739d37b16974",
      "source_system": "jackal",
      "source_event_type": "hunt",
      "signal_family": "divergence",
      "quality_label": null,
      "quality_score": 24.0,
      "reason": "divergence"
    },
    "068270.KS": {
      "ticker": "068270.KS",
      "name": "068270.KS",
      "market": "KR",
      "currency": "₩",
      "portfolio": false,
      "asset_type": "stock",
      "source": "candidate:hunt",
      "status": "open",
      "detected_at": "2026-05-28T23:53:26.601693+09:00",
      "candidate_id": "cand_a7da35f9da0347a28934bf45201ec763",
      "source_system": "jackal",
      "source_event_type": "hunt",
      "signal_family": "oversold_rebound",
      "quality_label": null,
      "quality_score": 29.0,
      "reason": "oversold_rebound"
    },
    "JPM": {
      "ticker": "JPM",
      "name": "JPM",
      "market": "US",
      "currency": "$",
      "portfolio": false,
      "asset_type": "stock",
      "source": "candidate:hunt",
      "status": "open",
      "detected_at": "2026-05-28T08:50:04.912716+09:00",
      "candidate_id": "cand_0cc047dc5b7847278f0df8fb3e07074a",
      "source_system": "jackal",
      "source_event_type": "hunt",
      "signal_family": "ma_reclaim",
      "quality_label": null,
      "quality_score": 24.0,
      "reason": "ma_reclaim"
    },
    "373220.KS": {
      "ticker": "373220.KS",
      "name": "373220.KS",
      "market": "KR",
      "currency": "₩",
      "portfolio": false,
      "asset_type": "stock",
      "source": "candidate:hunt",
      "status": "open",
      "detected_at": "2026-05-28T08:50:03.930228+09:00",
      "candidate_id": "cand_503723bece6b447bac16eff9305c3de1",
      "source_system": "jackal",
      "source_event_type": "hunt",
      "signal_family": "oversold_rebound",
      "quality_label": null,
      "quality_score": 24.0,
      "reason": "oversold_rebound"
    },
    "BA": {
      "ticker": "BA",
      "name": "BA",
      "market": "US",
      "currency": "$",
      "portfolio": false,
      "asset_type": "stock",
      "source": "candidate_registry",
      "status": "open",
      "detected_at": "2026-05-27T08:46:35.706291+09:00",
      "candidate_id": "cand_42237cd806cc409f9b3b444f193ff8fe",
      "source_system": "jackal",
      "source_event_type": "hunt",
      "signal_family": "divergence",
      "quality_label": null,
      "quality_score": 24.0
    },
    "NFLX": {
      "ticker": "NFLX",
      "name": "NFLX",
      "market": "US",
      "currency": "$",
      "portfolio": false,
      "asset_type": "stock",
      "source": "candidate_registry",
      "status": "open",
      "detected_at": "2026-05-26T23:18:56.285076+09:00",
      "candidate_id": "cand_891552be2b12416f82d6d535dc910164",
      "source_system": "jackal",
      "source_event_type": "hunt",
      "signal_family": "divergence",
      "quality_label": null,
      "quality_score": 24.0
    },
    "MSFT": {
      "ticker": "MSFT",
      "name": "MSFT",
      "market": "US",
      "currency": "$",
      "portfolio": false,
      "asset_type": "stock",
      "source": "candidate_registry",
      "status": "open",
      "detected_at": "2026-05-26T23:18:55.088860+09:00",
      "candidate_id": "cand_6f573db2049c4ae7817d0a012e1f8b33",
      "source_system": "jackal",
      "source_event_type": "hunt",
      "signal_family": "divergence",
      "quality_label": null,
      "quality_score": 29.0
    },
    "AMAT": {
      "ticker": "AMAT",
      "name": "AMAT",
      "market": "US",
      "currency": "$",
      "portfolio": false,
      "asset_type": "stock",
      "source": "candidate_registry",
      "status": "open",
      "detected_at": "2026-05-25T08:38:10.251350+09:00",
      "candidate_id": "cand_5f1b6b964a454431be8afc9939c29660",
      "source_system": "jackal",
      "source_event_type": "hunt",
      "signal_family": "divergence",
      "quality_label": null,
      "quality_score": 24.0
    },
    "096770.KS": {
      "ticker": "096770.KS",
      "name": "096770.KS",
      "market": "KR",
      "currency": "KRW",
      "portfolio": false,
      "asset_type": "stock",
      "source": "candidate_registry",
      "status": "open",
      "detected_at": "2026-05-22T22:47:44.711706+09:00",
      "candidate_id": "cand_d3de4beb332941159bc26eda7ad3f043",
      "source_system": "jackal",
      "source_event_type": "hunt",
      "signal_family": "ma_reclaim",
      "quality_label": null,
      "quality_score": 24.0
    },
    "010950.KS": {
      "ticker": "010950.KS",
      "name": "010950.KS",
      "market": "KR",
      "currency": "KRW",
      "portfolio": false,
      "asset_type": "stock",
      "source": "candidate_registry",
      "status": "open",
      "detected_at": "2026-05-22T22:47:44.452811+09:00",
      "candidate_id": "cand_d6de5640d19c4637acff2ad89369b42b",
      "source_system": "jackal",
      "source_event_type": "hunt",
      "signal_family": "rotation",
      "quality_label": null,
      "quality_score": 24.0
    },
    "035420.KS": {
      "ticker": "035420.KS",
      "name": "035420.KS",
      "market": "KR",
      "currency": "KRW",
      "portfolio": false,
      "asset_type": "stock",
      "source": "candidate_registry",
      "status": "open",
      "detected_at": "2026-05-21T08:53:48.106599+09:00",
      "candidate_id": "cand_85418bfaa04c44b48e49d29b4cae12a2",
      "source_system": "jackal",
      "source_event_type": "hunt",
      "signal_family": "panic_rebound",
      "quality_label": null,
      "quality_score": 24.0
    },
    "005380.KS": {
      "ticker": "005380.KS",
      "name": "005380.KS",
      "market": "KR",
      "currency": "KRW",
      "portfolio": false,
      "asset_type": "stock",
      "source": "candidate_registry",
      "status": "open",
      "detected_at": "2026-05-20T23:07:19.777890+09:00",
      "candidate_id": "cand_23ac0d1e8e704546957de2f923097f81",
      "source_system": "jackal",
      "source_event_type": "hunt",
      "signal_family": "oversold_rebound",
      "quality_label": null,
      "quality_score": 24.0
    },
    "000270.KS": {
      "ticker": "000270.KS",
      "name": "000270.KS",
      "market": "KR",
      "currency": "KRW",
      "portfolio": false,
      "asset_type": "stock",
      "source": "candidate_registry",
      "status": "open",
      "detected_at": "2026-05-20T23:07:19.639583+09:00",
      "candidate_id": "cand_3651b274380743b598fb91c5ad4e2b82",
      "source_system": "jackal",
      "source_event_type": "hunt",
      "signal_family": "oversold_rebound",
      "quality_label": null,
      "quality_score": 24.0
    },
    "META": {
      "ticker": "META",
      "name": "META",
      "market": "US",
      "currency": "$",
      "portfolio": false,
      "asset_type": "stock",
      "source": "candidate_registry",
      "status": "open",
      "detected_at": "2026-05-20T21:42:31.185525+09:00",
      "candidate_id": "cand_9fc42d84a19c4c12ad3a587ef2384080",
      "source_system": "jackal",
      "source_event_type": "hunt",
      "signal_family": "ma_reclaim",
      "quality_label": null,
      "quality_score": 24.0
    },
    "247540.KS": {
      "ticker": "247540.KS",
      "name": "247540.KS",
      "market": "KR",
      "currency": "KRW",
      "portfolio": false,
      "asset_type": "stock",
      "source": "candidate_registry",
      "status": "open",
      "detected_at": "2026-05-20T21:42:31.037225+09:00",
      "candidate_id": "cand_c571aa93821c4344b5e403aeb2735d3a",
      "source_system": "jackal",
      "source_event_type": "hunt",
      "signal_family": "panic_rebound",
      "quality_label": null,
      "quality_score": 24.0
    },
    "RIVN": {
      "ticker": "RIVN",
      "name": "RIVN",
      "market": "US",
      "currency": "$",
      "portfolio": false,
      "asset_type": "stock",
      "source": "candidate_registry",
      "status": "open",
      "detected_at": "2026-05-20T19:36:51.997133+09:00",
      "candidate_id": "cand_1186ebc2333d414f97884721a3c9a456",
      "source_system": "jackal",
      "source_event_type": "hunt",
      "signal_family": "divergence",
      "quality_label": null,
      "quality_score": 24.0
    },
    "BAC": {
      "ticker": "BAC",
      "name": "BAC",
      "market": "US",
      "currency": "$",
      "portfolio": false,
      "asset_type": "stock",
      "source": "candidate_registry",
      "status": "open",
      "detected_at": "2026-05-18T08:48:38.597770+09:00",
      "candidate_id": "cand_d3d8b1f1b0104bada50da5444035cced",
      "source_system": "jackal",
      "source_event_type": "hunt",
      "signal_family": "ma_reclaim",
      "quality_label": null,
      "quality_score": 29.0
    },
    "WFC": {
      "ticker": "WFC",
      "name": "WFC",
      "market": "US",
      "currency": "$",
      "portfolio": false,
      "asset_type": "stock",
      "source": "candidate_registry",
      "status": "open",
      "detected_at": "2026-05-18T08:48:38.534698+09:00",
      "candidate_id": "cand_02fabf8602c14b918b92abff10b17fdc",
      "source_system": "jackal",
      "source_event_type": "hunt",
      "signal_family": "oversold_rebound",
      "quality_label": null,
      "quality_score": 29.0
    },
    "PFE": {
      "ticker": "PFE",
      "name": "PFE",
      "market": "US",
      "currency": "$",
      "portfolio": false,
      "asset_type": "stock",
      "source": "candidate_registry",
      "status": "open",
      "detected_at": "2026-05-17T19:07:20.717681+09:00",
      "candidate_id": "cand_2e452780779e4125ac1a10fc5b20fcc2",
      "source_system": "jackal",
      "source_event_type": "hunt",
      "signal_family": "divergence",
      "quality_label": null,
      "quality_score": 24.0
    },
    "NVDA": {
      "ticker": "NVDA",
      "name": "엔비디아",
      "market": "US",
      "currency": "$",
      "portfolio": false,
      "asset_type": "stock",
      "source": "candidate_registry",
      "status": "open",
      "detected_at": "2026-05-08T21:24:48.272619+09:00",
      "candidate_id": "cand_8bb3e67b0502437e98e8599c7c71165b",
      "source_system": "jackal",
      "source_event_type": "scan",
      "signal_family": "general_rebound",
      "quality_label": "보통",
      "quality_score": 50.0
    },
    "000660.KS": {
      "ticker": "000660.KS",
      "name": "SK하이닉스",
      "market": "KR",
      "currency": "KRW",
      "portfolio": false,
      "asset_type": "stock",
      "source": "candidate_registry",
      "status": "open",
      "detected_at": "2026-05-08T21:24:48.272619+09:00",
      "candidate_id": "cand_e30c43a5b52e4bf2b25811cac0421140",
      "source_system": "jackal",
      "source_event_type": "shadow",
      "signal_family": "general_rebound",
      "quality_label": "약",
      "quality_score": 42.0
    },
    "005930.KS": {
      "ticker": "005930.KS",
      "name": "삼성전자",
      "market": "KR",
      "currency": "KRW",
      "portfolio": false,
      "asset_type": "stock",
      "source": "candidate_registry",
      "status": "open",
      "detected_at": "2026-05-08T21:24:48.272619+09:00",
      "candidate_id": "cand_d36cfefe7a144f38b9633a72064d5be2",
      "source_system": "jackal",
      "source_event_type": "shadow",
      "signal_family": "general_rebound",
      "quality_label": "약",
      "quality_score": 42.0
    },
    "AVGO": {
      "ticker": "AVGO",
      "name": "브로드컴",
      "market": "US",
      "currency": "$",
      "portfolio": false,
      "asset_type": "stock",
      "source": "candidate_registry",
      "status": "open",
      "detected_at": "2026-05-08T21:24:48.272619+09:00",
      "candidate_id": "cand_a47d5c48fa5e440894c1a6bfa4a3728d",
      "source_system": "jackal",
      "source_event_type": "scan",
      "signal_family": "general_rebound",
      "quality_label": "보통",
      "quality_score": 50.0
    },
    "466920.KS": {
      "ticker": "466920.KS",
      "name": "SOL 코리아고배당",
      "market": "KR",
      "currency": "KRW",
      "portfolio": false,
      "asset_type": "stock",
      "source": "candidate_registry",
      "status": "open",
      "detected_at": "2026-05-08T21:24:48.272619+09:00",
      "candidate_id": "cand_cbc6a6b925474bc58937920f905b0ad0",
      "source_system": "jackal",
      "source_event_type": "scan",
      "signal_family": "general_rebound",
      "quality_label": "보통",
      "quality_score": 50.0
    },
    "035720.KS": {
      "ticker": "035720.KS",
      "name": "카카오",
      "market": "KR",
      "currency": "KRW",
      "portfolio": false,
      "asset_type": "stock",
      "source": "candidate_registry",
      "status": "tracking",
      "detected_at": "2026-05-08T19:55:26.908597+09:00",
      "candidate_id": "cand_ce097a774e8c477f81f4a50d607ed978",
      "source_system": "jackal",
      "source_event_type": "scan",
      "signal_family": "rotation",
      "quality_label": "최강",
      "quality_score": 100.0
    }
  },
  "counts": {
    "total": 47,
    "portfolio": 0,
    "candidate": 16,
    "recommendation": 0
  }
}